{
  "definitions": {
    "Tag": {
      "type": "object",
      "properties": [
        {
          "name": "Key",
          "optional": false,
          "type": {
            "type": "string",
            "maxLength": 128,
            "minLength": 1,
            "pattern": "^([\\p{L}\\p{Z}\\p{N}_.:/=+\\-@]*)$"
          }
        },
        {
          "name": "Value",
          "optional": false,
          "type": {
            "type": "string",
            "maxLength": 256,
            "minLength": 0,
            "pattern": "^([\\p{L}\\p{Z}\\p{N}_.:/=+\\-@]*)$"
          }
        }
      ]
    }
  },
  "resource": {
    "type": "object",
    "description": "Definition of AWS::WorkSpacesWeb::UserAccessLoggingSettings Resource Type",
    "properties": [
      {
        "name": "KinesisStreamArn",
        "description": "Kinesis stream ARN to which log events are published.",
        "optional": false,
        "type": {
          "type": "string",
          "description": "Kinesis stream ARN to which log events are published.",
          "maxLength": 2048,
          "minLength": 20,
          "pattern": "arn:[\\w+=/,.@-]+:kinesis:[a-zA-Z0-9\\-]*:[a-zA-Z0-9]{1,12}:stream/.+"
        }
      },
      {
        "name": "Tags",
        "optional": true,
        "type": {
          "type": "array",
          "itemType": {
            "type": "ref",
            "typeName": "Tag"
          },
          "maxLength": 200,
          "minLength": 0
        }
      }
    ]
  },
  "attributes": {
    "type": "object",
    "description": "Definition of AWS::WorkSpacesWeb::UserAccessLoggingSettings Resource Type",
    "properties": [
      {
        "name": "AssociatedPortalArns",
        "optional": true,
        "type": {
          "type": "array",
          "itemType": {
            "type": "string",
            "maxLength": 2048,
            "minLength": 20,
            "pattern": "^arn:[\\w+=\\/,.@-]+:[a-zA-Z0-9\\-]+:[a-zA-Z0-9\\-]*:[a-zA-Z0-9]{1,12}:[a-zA-Z]+(\\/[a-fA-F0-9\\-]{36})+$"
          }
        }
      },
      {
        "name": "UserAccessLoggingSettingsArn",
        "optional": true,
        "type": {
          "type": "string",
          "maxLength": 2048,
          "minLength": 20,
          "pattern": "^arn:[\\w+=\\/,.@-]+:[a-zA-Z0-9\\-]+:[a-zA-Z0-9\\-]*:[a-zA-Z0-9]{1,12}:[a-zA-Z]+(\\/[a-fA-F0-9\\-]{36})+$"
        }
      }
    ]
  },
  "$hash": "d2938370995868a72d65efb00348beef37c6fcaf"
}
