{
  "definitions": {},
  "resource": {
    "type": "object",
    "description": "Definition of AWS::PCAConnectorAD::ServicePrincipalName Resource Type",
    "properties": [
      {
        "name": "ConnectorArn",
        "optional": true,
        "type": {
          "type": "string",
          "maxLength": 200,
          "minLength": 5,
          "pattern": "^arn:[\\w-]+:pca-connector-ad:[\\w-]+:[0-9]+:connector(\\/[\\w-]+)$"
        }
      },
      {
        "name": "DirectoryRegistrationArn",
        "optional": true,
        "type": {
          "type": "string",
          "maxLength": 200,
          "minLength": 5,
          "pattern": "^arn:[\\w-]+:pca-connector-ad:[\\w-]+:[0-9]+:directory-registration(\\/[\\w-]+)$"
        }
      }
    ]
  },
  "awsTypeName": "AWS::PCAConnectorAD::ServicePrincipalName",
  "$hash": "36c97dc2a031735ed0e79644e87cca3df532c27f"
}
