{
  "definitions": {
    "AccountId": {
      "type": "string",
      "description": "User account id, used as the primary identifier for the resource",
      "pattern": "^\\d{12}$"
    }
  },
  "resource": {
    "type": "object",
    "description": "This resource schema represents the LogAnomalyDetectionIntegration resource in the Amazon DevOps Guru.",
    "properties": []
  },
  "awsTypeName": "AWS::DevOpsGuru::LogAnomalyDetectionIntegration",
  "attributes": {
    "type": "object",
    "description": "This resource schema represents the LogAnomalyDetectionIntegration resource in the Amazon DevOps Guru.",
    "properties": [
      {
        "name": "AccountId",
        "optional": true,
        "type": {
          "type": "ref",
          "typeName": "AccountId"
        }
      }
    ]
  },
  "$hash": "d1aa500c5e0498c56a60e0dea16f181089b77d53"
}
