{
  "definitions": {},
  "resource": {
    "type": "object",
    "description": "Resource Type definition for AWS::AppStream::User",
    "properties": [
      {
        "name": "AuthenticationType",
        "optional": false,
        "type": {
          "type": "string"
        }
      },
      {
        "name": "FirstName",
        "optional": true,
        "type": {
          "type": "string"
        }
      },
      {
        "name": "LastName",
        "optional": true,
        "type": {
          "type": "string"
        }
      },
      {
        "name": "MessageAction",
        "optional": true,
        "type": {
          "type": "string"
        }
      },
      {
        "name": "UserName",
        "optional": false,
        "type": {
          "type": "string"
        }
      }
    ]
  },
  "typeName": "AWS::AppStream::User",
  "attributes": {
    "type": "object",
    "description": "Resource Type definition for AWS::AppStream::User",
    "properties": [
      {
        "name": "Id",
        "optional": true,
        "type": {
          "type": "string"
        }
      }
    ]
  },
  "$hash": "7edbe0fafd49190b29fd55447cf5a6932de281c9"
}
