{
  "definitions": {
    "RedisSettings": {
      "type": "object",
      "properties": [
        {
          "name": "SslSecurityProtocol",
          "optional": true,
          "type": {
            "type": "string"
          }
        },
        {
          "name": "AuthUserName",
          "optional": true,
          "type": {
            "type": "string"
          }
        },
        {
          "name": "ServerName",
          "optional": true,
          "type": {
            "type": "string"
          }
        },
        {
          "name": "Port",
          "optional": true,
          "type": {
            "type": "number",
            "isInteger": false
          }
        },
        {
          "name": "SslCaCertificateArn",
          "optional": true,
          "type": {
            "type": "string"
          }
        },
        {
          "name": "AuthPassword",
          "optional": true,
          "type": {
            "type": "string"
          }
        },
        {
          "name": "AuthType",
          "optional": true,
          "type": {
            "type": "string"
          }
        }
      ]
    },
    "SybaseSettings": {
      "type": "object",
      "properties": [
        {
          "name": "SecretsManagerAccessRoleArn",
          "optional": true,
          "type": {
            "type": "string"
          }
        },
        {
          "name": "SecretsManagerSecretId",
          "optional": true,
          "type": {
            "type": "string"
          }
        }
      ]
    },
    "IbmDb2Settings": {
      "type": "object",
      "properties": [
        {
          "name": "SecretsManagerSecretId",
          "optional": true,
          "type": {
            "type": "string"
          }
        },
        {
          "name": "SetDataCaptureChanges",
          "optional": true,
          "type": {
            "type": "boolean"
          }
        },
        {
          "name": "SecretsManagerAccessRoleArn",
          "optional": true,
          "type": {
            "type": "string"
          }
        },
        {
          "name": "CurrentLsn",
          "optional": true,
          "type": {
            "type": "string"
          }
        },
        {
          "name": "MaxKBytesPerRead",
          "optional": true,
          "type": {
            "type": "number",
            "isInteger": true
          }
        }
      ]
    },
    "OracleSettings": {
      "type": "object",
      "properties": [
        {
          "name": "AsmPassword",
          "optional": true,
          "type": {
            "type": "string"
          }
        },
        {
          "name": "DirectPathParallelLoad",
          "optional": true,
          "type": {
            "type": "boolean"
          }
        },
        {
          "name": "AdditionalArchivedLogDestId",
          "optional": true,
          "type": {
            "type": "number",
            "isInteger": true
          }
        },
        {
          "name": "SpatialDataOptionToGeoJsonFunctionName",
          "optional": true,
          "type": {
            "type": "string"
          }
        },
        {
          "name": "ReplacePathPrefix",
          "optional": true,
          "type": {
            "type": "boolean"
          }
        },
        {
          "name": "FailTasksOnLobTruncation",
          "optional": true,
          "type": {
            "type": "boolean"
          }
        },
        {
          "name": "AsmServer",
          "optional": true,
          "type": {
            "type": "string"
          }
        },
        {
          "name": "SecretsManagerOracleAsmAccessRoleArn",
          "optional": true,
          "type": {
            "type": "string"
          }
        },
        {
          "name": "OraclePathPrefix",
          "optional": true,
          "type": {
            "type": "string"
          }
        },
        {
          "name": "ReadAheadBlocks",
          "optional": true,
          "type": {
            "type": "number",
            "isInteger": true
          }
        },
        {
          "name": "StandbyDelayTime",
          "optional": true,
          "type": {
            "type": "number",
            "isInteger": true
          }
        },
        {
          "name": "AllowSelectNestedTables",
          "optional": true,
          "type": {
            "type": "boolean"
          }
        },
        {
          "name": "AddSupplementalLogging",
          "optional": true,
          "type": {
            "type": "boolean"
          }
        },
        {
          "name": "SecretsManagerSecretId",
          "optional": true,
          "type": {
            "type": "string"
          }
        },
        {
          "name": "UseBFile",
          "optional": true,
          "type": {
            "type": "boolean"
          }
        },
        {
          "name": "EnableHomogenousTablespace",
          "optional": true,
          "type": {
            "type": "boolean"
          }
        },
        {
          "name": "AsmUser",
          "optional": true,
          "type": {
            "type": "string"
          }
        },
        {
          "name": "UseDirectPathFullLoad",
          "optional": true,
          "type": {
            "type": "boolean"
          }
        },
        {
          "name": "SecurityDbEncryption",
          "optional": true,
          "type": {
            "type": "string"
          }
        },
        {
          "name": "ParallelAsmReadThreads",
          "optional": true,
          "type": {
            "type": "number",
            "isInteger": true
          }
        },
        {
          "name": "ArchivedLogDestId",
          "optional": true,
          "type": {
            "type": "number",
            "isInteger": true
          }
        },
        {
          "name": "UsePathPrefix",
          "optional": true,
          "type": {
            "type": "string"
          }
        },
        {
          "name": "UseLogminerReader",
          "optional": true,
          "type": {
            "type": "boolean"
          }
        },
        {
          "name": "SecurityDbEncryptionName",
          "optional": true,
          "type": {
            "type": "string"
          }
        },
        {
          "name": "DirectPathNoLog",
          "optional": true,
          "type": {
            "type": "boolean"
          }
        },
        {
          "name": "SecretsManagerOracleAsmSecretId",
          "optional": true,
          "type": {
            "type": "string"
          }
        },
        {
          "name": "CharLengthSemantics",
          "optional": true,
          "type": {
            "type": "string"
          }
        },
        {
          "name": "NumberDatatypeScale",
          "optional": true,
          "type": {
            "type": "number",
            "isInteger": true
          }
        },
        {
          "name": "ReadTableSpaceName",
          "optional": true,
          "type": {
            "type": "boolean"
          }
        },
        {
          "name": "AccessAlternateDirectly",
          "optional": true,
          "type": {
            "type": "boolean"
          }
        },
        {
          "name": "UseAlternateFolderForOnline",
          "optional": true,
          "type": {
            "type": "boolean"
          }
        },
        {
          "name": "ArchivedLogsOnly",
          "optional": true,
          "type": {
            "type": "boolean"
          }
        },
        {
          "name": "ExtraArchivedLogDestIds",
          "optional": true,
          "type": {
            "type": "array",
            "itemType": {
              "type": "number",
              "isInteger": true
            }
          }
        },
        {
          "name": "RetryInterval",
          "optional": true,
          "type": {
            "type": "number",
            "isInteger": true
          }
        },
        {
          "name": "SecretsManagerAccessRoleArn",
          "optional": true,
          "type": {
            "type": "string"
          }
        }
      ]
    },
    "KafkaSettings": {
      "type": "object",
      "properties": [
        {
          "name": "Broker",
          "optional": true,
          "type": {
            "type": "string"
          }
        },
        {
          "name": "SaslPassword",
          "optional": true,
          "type": {
            "type": "string"
          }
        },
        {
          "name": "MessageFormat",
          "optional": true,
          "type": {
            "type": "string"
          }
        },
        {
          "name": "SslClientCertificateArn",
          "optional": true,
          "type": {
            "type": "string"
          }
        },
        {
          "name": "IncludeTransactionDetails",
          "optional": true,
          "type": {
            "type": "boolean"
          }
        },
        {
          "name": "SecurityProtocol",
          "optional": true,
          "type": {
            "type": "string"
          }
        },
        {
          "name": "IncludeTableAlterOperations",
          "optional": true,
          "type": {
            "type": "boolean"
          }
        },
        {
          "name": "SslCaCertificateArn",
          "optional": true,
          "type": {
            "type": "string"
          }
        },
        {
          "name": "IncludeControlDetails",
          "optional": true,
          "type": {
            "type": "boolean"
          }
        },
        {
          "name": "IncludePartitionValue",
          "optional": true,
          "type": {
            "type": "boolean"
          }
        },
        {
          "name": "NoHexPrefix",
          "optional": true,
          "type": {
            "type": "boolean"
          }
        },
        {
          "name": "SslClientKeyArn",
          "optional": true,
          "type": {
            "type": "string"
          }
        },
        {
          "name": "SslClientKeyPassword",
          "optional": true,
          "type": {
            "type": "string"
          }
        },
        {
          "name": "SaslUserName",
          "optional": true,
          "type": {
            "type": "string"
          }
        },
        {
          "name": "MessageMaxBytes",
          "optional": true,
          "type": {
            "type": "number",
            "isInteger": true
          }
        },
        {
          "name": "Topic",
          "optional": true,
          "type": {
            "type": "string"
          }
        },
        {
          "name": "PartitionIncludeSchemaTable",
          "optional": true,
          "type": {
            "type": "boolean"
          }
        },
        {
          "name": "IncludeNullAndEmpty",
          "optional": true,
          "type": {
            "type": "boolean"
          }
        }
      ]
    },
    "MySqlSettings": {
      "type": "object",
      "properties": [
        {
          "name": "ServerTimezone",
          "optional": true,
          "type": {
            "type": "string"
          }
        },
        {
          "name": "EventsPollInterval",
          "optional": true,
          "type": {
            "type": "number",
            "isInteger": true
          }
        },
        {
          "name": "ParallelLoadThreads",
          "optional": true,
          "type": {
            "type": "number",
            "isInteger": true
          }
        },
        {
          "name": "AfterConnectScript",
          "optional": true,
          "type": {
            "type": "string"
          }
        },
        {
          "name": "MaxFileSize",
          "optional": true,
          "type": {
            "type": "number",
            "isInteger": true
          }
        },
        {
          "name": "TargetDbType",
          "optional": true,
          "type": {
            "type": "string"
          }
        },
        {
          "name": "SecretsManagerSecretId",
          "optional": true,
          "type": {
            "type": "string"
          }
        },
        {
          "name": "SecretsManagerAccessRoleArn",
          "optional": true,
          "type": {
            "type": "string"
          }
        },
        {
          "name": "CleanSourceMetadataOnMismatch",
          "optional": true,
          "type": {
            "type": "boolean"
          }
        }
      ]
    },
    "NeptuneSettings": {
      "type": "object",
      "properties": [
        {
          "name": "MaxRetryCount",
          "optional": true,
          "type": {
            "type": "number",
            "isInteger": true
          }
        },
        {
          "name": "MaxFileSize",
          "optional": true,
          "type": {
            "type": "number",
            "isInteger": true
          }
        },
        {
          "name": "S3BucketFolder",
          "optional": true,
          "type": {
            "type": "string"
          }
        },
        {
          "name": "ErrorRetryDuration",
          "optional": true,
          "type": {
            "type": "number",
            "isInteger": true
          }
        },
        {
          "name": "IamAuthEnabled",
          "optional": true,
          "type": {
            "type": "boolean"
          }
        },
        {
          "name": "S3BucketName",
          "optional": true,
          "type": {
            "type": "string"
          }
        },
        {
          "name": "ServiceAccessRoleArn",
          "optional": true,
          "type": {
            "type": "string"
          }
        }
      ]
    },
    "ElasticsearchSettings": {
      "type": "object",
      "properties": [
        {
          "name": "EndpointUri",
          "optional": true,
          "type": {
            "type": "string"
          }
        },
        {
          "name": "ErrorRetryDuration",
          "optional": true,
          "type": {
            "type": "number",
            "isInteger": true
          }
        },
        {
          "name": "FullLoadErrorPercentage",
          "optional": true,
          "type": {
            "type": "number",
            "isInteger": true
          }
        },
        {
          "name": "ServiceAccessRoleArn",
          "optional": true,
          "type": {
            "type": "string"
          }
        }
      ]
    },
    "S3Settings": {
      "type": "object",
      "properties": [
        {
          "name": "TimestampColumnName",
          "optional": true,
          "type": {
            "type": "string"
          }
        },
        {
          "name": "EnableStatistics",
          "optional": true,
          "type": {
            "type": "boolean"
          }
        },
        {
          "name": "DatePartitionSequence",
          "optional": true,
          "type": {
            "type": "string"
          }
        },
        {
          "name": "IncludeOpForFullLoad",
          "optional": true,
          "type": {
            "type": "boolean"
          }
        },
        {
          "name": "CsvNullValue",
          "optional": true,
          "type": {
            "type": "string"
          }
        },
        {
          "name": "CdcInsertsAndUpdates",
          "optional": true,
          "type": {
            "type": "boolean"
          }
        },
        {
          "name": "BucketName",
          "optional": true,
          "type": {
            "type": "string"
          }
        },
        {
          "name": "ServerSideEncryptionKmsKeyId",
          "optional": true,
          "type": {
            "type": "string"
          }
        },
        {
          "name": "UseTaskStartTimeForFullLoadTimestamp",
          "optional": true,
          "type": {
            "type": "boolean"
          }
        },
        {
          "name": "DataFormat",
          "optional": true,
          "type": {
            "type": "string"
          }
        },
        {
          "name": "CsvDelimiter",
          "optional": true,
          "type": {
            "type": "string"
          }
        },
        {
          "name": "IgnoreHeaderRows",
          "optional": true,
          "type": {
            "type": "number",
            "isInteger": true
          }
        },
        {
          "name": "CannedAclForObjects",
          "optional": true,
          "type": {
            "type": "string"
          }
        },
        {
          "name": "Rfc4180",
          "optional": true,
          "type": {
            "type": "boolean"
          }
        },
        {
          "name": "ServiceAccessRoleArn",
          "optional": true,
          "type": {
            "type": "string"
          }
        },
        {
          "name": "ParquetTimestampInMillisecond",
          "optional": true,
          "type": {
            "type": "boolean"
          }
        },
        {
          "name": "PreserveTransactions",
          "optional": true,
          "type": {
            "type": "boolean"
          }
        },
        {
          "name": "BucketFolder",
          "optional": true,
          "type": {
            "type": "string"
          }
        },
        {
          "name": "DatePartitionDelimiter",
          "optional": true,
          "type": {
            "type": "string"
          }
        },
        {
          "name": "EncodingType",
          "optional": true,
          "type": {
            "type": "string"
          }
        },
        {
          "name": "ParquetVersion",
          "optional": true,
          "type": {
            "type": "string"
          }
        },
        {
          "name": "AddColumnName",
          "optional": true,
          "type": {
            "type": "boolean"
          }
        },
        {
          "name": "CdcMinFileSize",
          "optional": true,
          "type": {
            "type": "number",
            "isInteger": true
          }
        },
        {
          "name": "ExternalTableDefinition",
          "optional": true,
          "type": {
            "type": "string"
          }
        },
        {
          "name": "UseCsvNoSupValue",
          "optional": true,
          "type": {
            "type": "boolean"
          }
        },
        {
          "name": "MaxFileSize",
          "optional": true,
          "type": {
            "type": "number",
            "isInteger": true
          }
        },
        {
          "name": "CsvNoSupValue",
          "optional": true,
          "type": {
            "type": "string"
          }
        },
        {
          "name": "CdcPath",
          "optional": true,
          "type": {
            "type": "string"
          }
        },
        {
          "name": "CsvRowDelimiter",
          "optional": true,
          "type": {
            "type": "string"
          }
        },
        {
          "name": "RowGroupLength",
          "optional": true,
          "type": {
            "type": "number",
            "isInteger": true
          }
        },
        {
          "name": "CdcMaxBatchInterval",
          "optional": true,
          "type": {
            "type": "number",
            "isInteger": true
          }
        },
        {
          "name": "DataPageSize",
          "optional": true,
          "type": {
            "type": "number",
            "isInteger": true
          }
        },
        {
          "name": "DictPageSizeLimit",
          "optional": true,
          "type": {
            "type": "number",
            "isInteger": true
          }
        },
        {
          "name": "DatePartitionEnabled",
          "optional": true,
          "type": {
            "type": "boolean"
          }
        },
        {
          "name": "CompressionType",
          "optional": true,
          "type": {
            "type": "string"
          }
        },
        {
          "name": "DatePartitionTimezone",
          "optional": true,
          "type": {
            "type": "string"
          }
        },
        {
          "name": "CdcInsertsOnly",
          "optional": true,
          "type": {
            "type": "boolean"
          }
        },
        {
          "name": "EncryptionMode",
          "optional": true,
          "type": {
            "type": "string"
          }
        }
      ]
    },
    "DocDbSettings": {
      "type": "object",
      "properties": [
        {
          "name": "SecretsManagerSecretId",
          "optional": true,
          "type": {
            "type": "string"
          }
        },
        {
          "name": "DocsToInvestigate",
          "optional": true,
          "type": {
            "type": "number",
            "isInteger": true
          }
        },
        {
          "name": "SecretsManagerAccessRoleArn",
          "optional": true,
          "type": {
            "type": "string"
          }
        },
        {
          "name": "ExtractDocId",
          "optional": true,
          "type": {
            "type": "boolean"
          }
        },
        {
          "name": "NestingLevel",
          "optional": true,
          "type": {
            "type": "string"
          }
        }
      ]
    },
    "DynamoDbSettings": {
      "type": "object",
      "properties": [
        {
          "name": "ServiceAccessRoleArn",
          "optional": true,
          "type": {
            "type": "string"
          }
        }
      ]
    },
    "KinesisSettings": {
      "type": "object",
      "properties": [
        {
          "name": "MessageFormat",
          "optional": true,
          "type": {
            "type": "string"
          }
        },
        {
          "name": "IncludeTransactionDetails",
          "optional": true,
          "type": {
            "type": "boolean"
          }
        },
        {
          "name": "IncludeTableAlterOperations",
          "optional": true,
          "type": {
            "type": "boolean"
          }
        },
        {
          "name": "IncludeControlDetails",
          "optional": true,
          "type": {
            "type": "boolean"
          }
        },
        {
          "name": "IncludePartitionValue",
          "optional": true,
          "type": {
            "type": "boolean"
          }
        },
        {
          "name": "StreamArn",
          "optional": true,
          "type": {
            "type": "string"
          }
        },
        {
          "name": "ServiceAccessRoleArn",
          "optional": true,
          "type": {
            "type": "string"
          }
        },
        {
          "name": "NoHexPrefix",
          "optional": true,
          "type": {
            "type": "boolean"
          }
        },
        {
          "name": "PartitionIncludeSchemaTable",
          "optional": true,
          "type": {
            "type": "boolean"
          }
        },
        {
          "name": "IncludeNullAndEmpty",
          "optional": true,
          "type": {
            "type": "boolean"
          }
        }
      ]
    },
    "GcpMySQLSettings": {
      "type": "object",
      "properties": [
        {
          "name": "AfterConnectScript",
          "optional": true,
          "type": {
            "type": "string"
          }
        },
        {
          "name": "Port",
          "optional": true,
          "type": {
            "type": "number",
            "isInteger": true
          }
        },
        {
          "name": "DatabaseName",
          "optional": true,
          "type": {
            "type": "string"
          }
        },
        {
          "name": "CleanSourceMetadataOnMismatch",
          "optional": true,
          "type": {
            "type": "boolean"
          }
        },
        {
          "name": "ServerTimezone",
          "optional": true,
          "type": {
            "type": "string"
          }
        },
        {
          "name": "EventsPollInterval",
          "optional": true,
          "type": {
            "type": "number",
            "isInteger": true
          }
        },
        {
          "name": "ParallelLoadThreads",
          "optional": true,
          "type": {
            "type": "number",
            "isInteger": true
          }
        },
        {
          "name": "Username",
          "optional": true,
          "type": {
            "type": "string"
          }
        },
        {
          "name": "MaxFileSize",
          "optional": true,
          "type": {
            "type": "number",
            "isInteger": true
          }
        },
        {
          "name": "ServerName",
          "optional": true,
          "type": {
            "type": "string"
          }
        },
        {
          "name": "SecretsManagerSecretId",
          "optional": true,
          "type": {
            "type": "string"
          }
        },
        {
          "name": "SecretsManagerAccessRoleArn",
          "optional": true,
          "type": {
            "type": "string"
          }
        },
        {
          "name": "Password",
          "optional": true,
          "type": {
            "type": "string"
          }
        }
      ]
    },
    "MicrosoftSqlServerSettings": {
      "type": "object",
      "properties": [
        {
          "name": "ReadBackupOnly",
          "optional": true,
          "type": {
            "type": "boolean"
          }
        },
        {
          "name": "TlogAccessMode",
          "optional": true,
          "type": {
            "type": "string"
          }
        },
        {
          "name": "BcpPacketSize",
          "optional": true,
          "type": {
            "type": "number",
            "isInteger": true
          }
        },
        {
          "name": "Port",
          "optional": true,
          "type": {
            "type": "number",
            "isInteger": true
          }
        },
        {
          "name": "SafeguardPolicy",
          "optional": true,
          "type": {
            "type": "string"
          }
        },
        {
          "name": "UseThirdPartyBackupDevice",
          "optional": true,
          "type": {
            "type": "boolean"
          }
        },
        {
          "name": "DatabaseName",
          "optional": true,
          "type": {
            "type": "string"
          }
        },
        {
          "name": "UseBcpFullLoad",
          "optional": true,
          "type": {
            "type": "boolean"
          }
        },
        {
          "name": "Username",
          "optional": true,
          "type": {
            "type": "string"
          }
        },
        {
          "name": "QuerySingleAlwaysOnNode",
          "optional": true,
          "type": {
            "type": "boolean"
          }
        },
        {
          "name": "ServerName",
          "optional": true,
          "type": {
            "type": "string"
          }
        },
        {
          "name": "SecretsManagerSecretId",
          "optional": true,
          "type": {
            "type": "string"
          }
        },
        {
          "name": "ControlTablesFileGroup",
          "optional": true,
          "type": {
            "type": "string"
          }
        },
        {
          "name": "ForceLobLookup",
          "optional": true,
          "type": {
            "type": "boolean"
          }
        },
        {
          "name": "SecretsManagerAccessRoleArn",
          "optional": true,
          "type": {
            "type": "string"
          }
        },
        {
          "name": "TrimSpaceInChar",
          "optional": true,
          "type": {
            "type": "boolean"
          }
        },
        {
          "name": "Password",
          "optional": true,
          "type": {
            "type": "string"
          }
        }
      ]
    },
    "RedshiftSettings": {
      "type": "object",
      "properties": [
        {
          "name": "ConnectionTimeout",
          "optional": true,
          "type": {
            "type": "number",
            "isInteger": true
          }
        },
        {
          "name": "MapBooleanAsBoolean",
          "optional": true,
          "type": {
            "type": "boolean"
          }
        },
        {
          "name": "AfterConnectScript",
          "optional": true,
          "type": {
            "type": "string"
          }
        },
        {
          "name": "FileTransferUploadStreams",
          "optional": true,
          "type": {
            "type": "number",
            "isInteger": true
          }
        },
        {
          "name": "BucketName",
          "optional": true,
          "type": {
            "type": "string"
          }
        },
        {
          "name": "ServerSideEncryptionKmsKeyId",
          "optional": true,
          "type": {
            "type": "string"
          }
        },
        {
          "name": "ExplicitIds",
          "optional": true,
          "type": {
            "type": "boolean"
          }
        },
        {
          "name": "SecretsManagerSecretId",
          "optional": true,
          "type": {
            "type": "string"
          }
        },
        {
          "name": "TruncateColumns",
          "optional": true,
          "type": {
            "type": "boolean"
          }
        },
        {
          "name": "ServiceAccessRoleArn",
          "optional": true,
          "type": {
            "type": "string"
          }
        },
        {
          "name": "ReplaceChars",
          "optional": true,
          "type": {
            "type": "string"
          }
        },
        {
          "name": "TimeFormat",
          "optional": true,
          "type": {
            "type": "string"
          }
        },
        {
          "name": "BucketFolder",
          "optional": true,
          "type": {
            "type": "string"
          }
        },
        {
          "name": "ReplaceInvalidChars",
          "optional": true,
          "type": {
            "type": "string"
          }
        },
        {
          "name": "RemoveQuotes",
          "optional": true,
          "type": {
            "type": "boolean"
          }
        },
        {
          "name": "LoadTimeout",
          "optional": true,
          "type": {
            "type": "number",
            "isInteger": true
          }
        },
        {
          "name": "MaxFileSize",
          "optional": true,
          "type": {
            "type": "number",
            "isInteger": true
          }
        },
        {
          "name": "TrimBlanks",
          "optional": true,
          "type": {
            "type": "boolean"
          }
        },
        {
          "name": "DateFormat",
          "optional": true,
          "type": {
            "type": "string"
          }
        },
        {
          "name": "CompUpdate",
          "optional": true,
          "type": {
            "type": "boolean"
          }
        },
        {
          "name": "AcceptAnyDate",
          "optional": true,
          "type": {
            "type": "boolean"
          }
        },
        {
          "name": "WriteBufferSize",
          "optional": true,
          "type": {
            "type": "number",
            "isInteger": true
          }
        },
        {
          "name": "SecretsManagerAccessRoleArn",
          "optional": true,
          "type": {
            "type": "string"
          }
        },
        {
          "name": "CaseSensitiveNames",
          "optional": true,
          "type": {
            "type": "boolean"
          }
        },
        {
          "name": "EmptyAsNull",
          "optional": true,
          "type": {
            "type": "boolean"
          }
        },
        {
          "name": "EncryptionMode",
          "optional": true,
          "type": {
            "type": "string"
          }
        }
      ]
    },
    "Tag": {
      "type": "object",
      "properties": [
        {
          "name": "Value",
          "optional": false,
          "type": {
            "type": "string"
          }
        },
        {
          "name": "Key",
          "optional": false,
          "type": {
            "type": "string"
          }
        }
      ]
    },
    "MongoDbSettings": {
      "type": "object",
      "properties": [
        {
          "name": "Port",
          "optional": true,
          "type": {
            "type": "number",
            "isInteger": true
          }
        },
        {
          "name": "ExtractDocId",
          "optional": true,
          "type": {
            "type": "string"
          }
        },
        {
          "name": "DatabaseName",
          "optional": true,
          "type": {
            "type": "string"
          }
        },
        {
          "name": "AuthSource",
          "optional": true,
          "type": {
            "type": "string"
          }
        },
        {
          "name": "AuthMechanism",
          "optional": true,
          "type": {
            "type": "string"
          }
        },
        {
          "name": "Username",
          "optional": true,
          "type": {
            "type": "string"
          }
        },
        {
          "name": "DocsToInvestigate",
          "optional": true,
          "type": {
            "type": "string"
          }
        },
        {
          "name": "ServerName",
          "optional": true,
          "type": {
            "type": "string"
          }
        },
        {
          "name": "SecretsManagerSecretId",
          "optional": true,
          "type": {
            "type": "string"
          }
        },
        {
          "name": "AuthType",
          "optional": true,
          "type": {
            "type": "string"
          }
        },
        {
          "name": "SecretsManagerAccessRoleArn",
          "optional": true,
          "type": {
            "type": "string"
          }
        },
        {
          "name": "Password",
          "optional": true,
          "type": {
            "type": "string"
          }
        },
        {
          "name": "NestingLevel",
          "optional": true,
          "type": {
            "type": "string"
          }
        }
      ]
    },
    "PostgreSqlSettings": {
      "type": "object",
      "properties": [
        {
          "name": "PluginName",
          "optional": true,
          "type": {
            "type": "string"
          }
        },
        {
          "name": "MapBooleanAsBoolean",
          "optional": true,
          "type": {
            "type": "boolean"
          }
        },
        {
          "name": "AfterConnectScript",
          "optional": true,
          "type": {
            "type": "string"
          }
        },
        {
          "name": "ExecuteTimeout",
          "optional": true,
          "type": {
            "type": "number",
            "isInteger": true
          }
        },
        {
          "name": "DdlArtifactsSchema",
          "optional": true,
          "type": {
            "type": "string"
          }
        },
        {
          "name": "FailTasksOnLobTruncation",
          "optional": true,
          "type": {
            "type": "boolean"
          }
        },
        {
          "name": "HeartbeatEnable",
          "optional": true,
          "type": {
            "type": "boolean"
          }
        },
        {
          "name": "BabelfishDatabaseName",
          "optional": true,
          "type": {
            "type": "string"
          }
        },
        {
          "name": "DatabaseMode",
          "optional": true,
          "type": {
            "type": "string"
          }
        },
        {
          "name": "CaptureDdls",
          "optional": true,
          "type": {
            "type": "boolean"
          }
        },
        {
          "name": "MaxFileSize",
          "optional": true,
          "type": {
            "type": "number",
            "isInteger": true
          }
        },
        {
          "name": "HeartbeatFrequency",
          "optional": true,
          "type": {
            "type": "number",
            "isInteger": true
          }
        },
        {
          "name": "SecretsManagerSecretId",
          "optional": true,
          "type": {
            "type": "string"
          }
        },
        {
          "name": "SecretsManagerAccessRoleArn",
          "optional": true,
          "type": {
            "type": "string"
          }
        },
        {
          "name": "HeartbeatSchema",
          "optional": true,
          "type": {
            "type": "string"
          }
        },
        {
          "name": "SlotName",
          "optional": true,
          "type": {
            "type": "string"
          }
        }
      ]
    }
  },
  "resource": {
    "type": "object",
    "description": "Resource Type definition for AWS::DMS::Endpoint",
    "properties": [
      {
        "name": "SybaseSettings",
        "optional": true,
        "type": {
          "type": "ref",
          "typeName": "SybaseSettings"
        }
      },
      {
        "name": "RedisSettings",
        "optional": true,
        "type": {
          "type": "ref",
          "typeName": "RedisSettings"
        }
      },
      {
        "name": "OracleSettings",
        "optional": true,
        "type": {
          "type": "ref",
          "typeName": "OracleSettings"
        }
      },
      {
        "name": "KafkaSettings",
        "optional": true,
        "type": {
          "type": "ref",
          "typeName": "KafkaSettings"
        }
      },
      {
        "name": "Port",
        "optional": true,
        "type": {
          "type": "number",
          "isInteger": true
        }
      },
      {
        "name": "MySqlSettings",
        "optional": true,
        "type": {
          "type": "ref",
          "typeName": "MySqlSettings"
        }
      },
      {
        "name": "S3Settings",
        "optional": true,
        "type": {
          "type": "ref",
          "typeName": "S3Settings"
        }
      },
      {
        "name": "ResourceIdentifier",
        "optional": true,
        "type": {
          "type": "string"
        }
      },
      {
        "name": "KinesisSettings",
        "optional": true,
        "type": {
          "type": "ref",
          "typeName": "KinesisSettings"
        }
      },
      {
        "name": "SslMode",
        "optional": true,
        "type": {
          "type": "string"
        }
      },
      {
        "name": "RedshiftSettings",
        "optional": true,
        "type": {
          "type": "ref",
          "typeName": "RedshiftSettings"
        }
      },
      {
        "name": "EndpointType",
        "optional": false,
        "type": {
          "type": "string"
        }
      },
      {
        "name": "Tags",
        "optional": true,
        "type": {
          "type": "array",
          "itemType": {
            "type": "ref",
            "typeName": "Tag"
          }
        }
      },
      {
        "name": "Password",
        "optional": true,
        "type": {
          "type": "string"
        }
      },
      {
        "name": "MongoDbSettings",
        "optional": true,
        "type": {
          "type": "ref",
          "typeName": "MongoDbSettings"
        }
      },
      {
        "name": "IbmDb2Settings",
        "optional": true,
        "type": {
          "type": "ref",
          "typeName": "IbmDb2Settings"
        }
      },
      {
        "name": "KmsKeyId",
        "optional": true,
        "type": {
          "type": "string"
        }
      },
      {
        "name": "DatabaseName",
        "optional": true,
        "type": {
          "type": "string"
        }
      },
      {
        "name": "NeptuneSettings",
        "optional": true,
        "type": {
          "type": "ref",
          "typeName": "NeptuneSettings"
        }
      },
      {
        "name": "ElasticsearchSettings",
        "optional": true,
        "type": {
          "type": "ref",
          "typeName": "ElasticsearchSettings"
        }
      },
      {
        "name": "EngineName",
        "optional": false,
        "type": {
          "type": "string"
        }
      },
      {
        "name": "DocDbSettings",
        "optional": true,
        "type": {
          "type": "ref",
          "typeName": "DocDbSettings"
        }
      },
      {
        "name": "DynamoDbSettings",
        "optional": true,
        "type": {
          "type": "ref",
          "typeName": "DynamoDbSettings"
        }
      },
      {
        "name": "Username",
        "optional": true,
        "type": {
          "type": "string"
        }
      },
      {
        "name": "MicrosoftSqlServerSettings",
        "optional": true,
        "type": {
          "type": "ref",
          "typeName": "MicrosoftSqlServerSettings"
        }
      },
      {
        "name": "GcpMySQLSettings",
        "optional": true,
        "type": {
          "type": "ref",
          "typeName": "GcpMySQLSettings"
        }
      },
      {
        "name": "ServerName",
        "optional": true,
        "type": {
          "type": "string"
        }
      },
      {
        "name": "ExtraConnectionAttributes",
        "optional": true,
        "type": {
          "type": "string"
        }
      },
      {
        "name": "EndpointIdentifier",
        "optional": true,
        "type": {
          "type": "string"
        }
      },
      {
        "name": "CertificateArn",
        "optional": true,
        "type": {
          "type": "string"
        }
      },
      {
        "name": "PostgreSqlSettings",
        "optional": true,
        "type": {
          "type": "ref",
          "typeName": "PostgreSqlSettings"
        }
      }
    ]
  },
  "attributes": {
    "type": "object",
    "description": "Resource Type definition for AWS::DMS::Endpoint",
    "properties": [
      {
        "name": "ExternalId",
        "optional": true,
        "type": {
          "type": "string"
        }
      },
      {
        "name": "Id",
        "optional": true,
        "type": {
          "type": "string"
        }
      }
    ]
  },
  "$hash": "0dbbcc50a24cc9889c2ec8f172c4e9224a21cd03"
}
