{
  "definitions": {
    "Tag": {
      "type": "object",
      "properties": [
        {
          "name": "Key",
          "optional": false,
          "type": {
            "type": "string"
          }
        },
        {
          "name": "Value",
          "optional": false,
          "type": {
            "type": "string"
          }
        }
      ]
    }
  },
  "resource": {
    "type": "object",
    "description": "Resource Type definition for AWS::EC2::Subnet",
    "properties": [
      {
        "name": "AssignIpv6AddressOnCreation",
        "optional": true,
        "type": {
          "type": "boolean"
        }
      },
      {
        "name": "AvailabilityZone",
        "optional": true,
        "type": {
          "type": "string"
        }
      },
      {
        "name": "AvailabilityZoneId",
        "optional": true,
        "type": {
          "type": "string"
        }
      },
      {
        "name": "CidrBlock",
        "optional": true,
        "type": {
          "type": "string"
        }
      },
      {
        "name": "EnableDns64",
        "optional": true,
        "type": {
          "type": "boolean"
        }
      },
      {
        "name": "Ipv4NetmaskLength",
        "description": "The netmask length of the IPv4 CIDR you want to allocate to this subnet from an Amazon VPC IP Address Manager (IPAM) pool",
        "optional": true,
        "type": {
          "type": "number",
          "description": "The netmask length of the IPv4 CIDR you want to allocate to this subnet from an Amazon VPC IP Address Manager (IPAM) pool",
          "isInteger": true
        }
      },
      {
        "name": "Ipv6CidrBlock",
        "optional": true,
        "type": {
          "type": "string"
        }
      },
      {
        "name": "Ipv6Native",
        "optional": true,
        "type": {
          "type": "boolean"
        }
      },
      {
        "name": "Ipv6NetmaskLength",
        "description": "The netmask length of the IPv6 CIDR you want to allocate to this subnet from an Amazon VPC IP Address Manager (IPAM) pool",
        "optional": true,
        "type": {
          "type": "number",
          "description": "The netmask length of the IPv6 CIDR you want to allocate to this subnet from an Amazon VPC IP Address Manager (IPAM) pool",
          "isInteger": true
        }
      },
      {
        "name": "MapPublicIpOnLaunch",
        "optional": true,
        "type": {
          "type": "boolean"
        }
      },
      {
        "name": "OutpostArn",
        "optional": true,
        "type": {
          "type": "string"
        }
      },
      {
        "name": "PrivateDnsNameOptionsOnLaunch",
        "optional": true,
        "type": {
          "type": "object",
          "properties": [
            {
              "name": "EnableResourceNameDnsAAAARecord",
              "optional": true,
              "type": {
                "type": "boolean"
              }
            },
            {
              "name": "EnableResourceNameDnsARecord",
              "optional": true,
              "type": {
                "type": "boolean"
              }
            },
            {
              "name": "HostnameType",
              "optional": true,
              "type": {
                "type": "string"
              }
            }
          ]
        }
      },
      {
        "name": "Tags",
        "optional": true,
        "type": {
          "type": "array",
          "itemType": {
            "type": "ref",
            "typeName": "Tag"
          }
        }
      },
      {
        "name": "VpcId",
        "optional": false,
        "type": {
          "type": "string"
        }
      }
    ]
  },
  "typeName": "AWS::EC2::Subnet",
  "attributes": {
    "type": "object",
    "description": "Resource Type definition for AWS::EC2::Subnet",
    "properties": [
      {
        "name": "Ipv6CidrBlocks",
        "optional": true,
        "type": {
          "type": "array",
          "itemType": {
            "type": "string"
          }
        }
      },
      {
        "name": "NetworkAclAssociationId",
        "optional": true,
        "type": {
          "type": "string"
        }
      },
      {
        "name": "SubnetId",
        "optional": true,
        "type": {
          "type": "string"
        }
      }
    ]
  },
  "$hash": "7a5389a62429231a674537d83a84e325fecb8176"
}
