{
  "definitions": {
    "Tags": {
      "type": "object",
      "properties": [
        {
          "name": "Value",
          "optional": true,
          "type": {
            "type": "string"
          }
        },
        {
          "name": "Key",
          "optional": true,
          "type": {
            "type": "string"
          }
        }
      ]
    }
  },
  "resource": {
    "type": "object",
    "description": "Resource Type definition for AWS::AppConfig::DeploymentStrategy",
    "properties": [
      {
        "name": "ReplicateTo",
        "optional": false,
        "type": {
          "type": "string"
        }
      },
      {
        "name": "GrowthType",
        "optional": true,
        "type": {
          "type": "string"
        }
      },
      {
        "name": "Description",
        "optional": true,
        "type": {
          "type": "string"
        }
      },
      {
        "name": "DeploymentDurationInMinutes",
        "optional": false,
        "type": {
          "type": "number",
          "isInteger": false
        }
      },
      {
        "name": "GrowthFactor",
        "optional": false,
        "type": {
          "type": "number",
          "isInteger": false
        }
      },
      {
        "name": "FinalBakeTimeInMinutes",
        "optional": true,
        "type": {
          "type": "number",
          "isInteger": false
        }
      },
      {
        "name": "Tags",
        "optional": true,
        "type": {
          "type": "array",
          "itemType": {
            "type": "ref",
            "typeName": "Tags"
          }
        }
      },
      {
        "name": "Name",
        "optional": false,
        "type": {
          "type": "string"
        }
      }
    ]
  },
  "attributes": {
    "type": "object",
    "description": "Resource Type definition for AWS::AppConfig::DeploymentStrategy",
    "properties": [
      {
        "name": "Id",
        "optional": true,
        "type": {
          "type": "string"
        }
      }
    ]
  },
  "$hash": "1441d8555492a2e252e0d8f883b607e2bb7b5976"
}
